{
  "slug": "cap-m48865-14x21x8cm-gf-2019646",
  "top_category": "Bags",
  "source_site": "bags",
  "source_domain": "bags.tangma2088.com",
  "source_top_category": "Bags",
  "source_category": "New Products",
  "source_category_original": "new",
  "source_product_id": "2019652",
  "source_parent_product_id": "2019646",
  "source_product_url": "https://bags.tangma2088.com/productinfoen_2019652.html",
  "source_canonical_url": "https://trendholic.github.io/catalog/product/cap-m48865-14x21x8cm-gf-2019646/",
  "source_product_urls": [
    "https://bags.tangma2088.com/productinfoen_2019652.html",
    "https://bags.tangma2088.com/productinfoen_2019651.html",
    "https://bags.tangma2088.com/productinfoen_2019650.html",
    "https://bags.tangma2088.com/productinfoen_2019649.html",
    "https://bags.tangma2088.com/productinfoen_2019648.html",
    "https://bags.tangma2088.com/productinfoen_2019647.html",
    "https://bags.tangma2088.com/productinfoen_2019646.html"
  ],
  "source_image_urls": [
    "https://bags.tangma2088.com/upfile/product/202607/Cap%20M48865%2014x21x8cm%20gf71_2019646.jpg",
    "https://bags.tangma2088.com/upfile/product/202607/Cap%20M48865%2014x21x8cm%20gf72_2019647.jpg",
    "https://bags.tangma2088.com/upfile/product/202607/Cap%20M48865%2014x21x8cm%20gf73_2019648.jpg",
    "https://bags.tangma2088.com/upfile/product/202607/Cap%20M48865%2014x21x8cm%20gf74_2019649.jpg"
  ],
  "source_last_seen": "2026-07-24T06:21:34.958Z",
  "name": "Cap M48865 14x21x8cm gf",
  "english_product_name": "Cap M48865 14x21x8cm gf",
  "original_product_name": null,
  "brand": null,
  "sku": null,
  "model_number": null,
  "product_code": null,
  "product_id": "2019646",
  "parent_product_id": "2019646",
  "description": null,
  "features": [],
  "specifications": null,
  "materials": null,
  "color": null,
  "size": null,
  "variants": [],
  "dimensions": null,
  "weight": null,
  "packaging": null,
  "moq": null,
  "price": null,
  "currency": null,
  "availability": null,
  "images": [
    {
      "src": "/data/bags/images/cap-m48865-14x21x8cm-gf-2019646-1.webp",
      "source_url": "https://bags.tangma2088.com/upfile/product/202607/Cap%20M48865%2014x21x8cm%20gf71_2019646.jpg",
      "content_hash": "e4495d759621280995aab709508694601a2710b0",
      "alt": "Cap M48865 14x21x8cm gf"
    },
    {
      "src": "/data/bags/images/cap-m48865-14x21x8cm-gf-2019646-2.webp",
      "source_url": "https://bags.tangma2088.com/upfile/product/202607/Cap%20M48865%2014x21x8cm%20gf72_2019647.jpg",
      "content_hash": "d488d436c9927f58a0697d63cbf6b506a192f2b0",
      "alt": "Cap M48865 14x21x8cm gf"
    },
    {
      "src": "/data/bags/images/cap-m48865-14x21x8cm-gf-2019646-3.webp",
      "source_url": "https://bags.tangma2088.com/upfile/product/202607/Cap%20M48865%2014x21x8cm%20gf73_2019648.jpg",
      "content_hash": "46708b54fb40b4f5116d812237af3af0b6ff5f61",
      "alt": "Cap M48865 14x21x8cm gf"
    },
    {
      "src": "/data/bags/images/cap-m48865-14x21x8cm-gf-2019646-4.webp",
      "source_url": "https://bags.tangma2088.com/upfile/product/202607/Cap%20M48865%2014x21x8cm%20gf74_2019649.jpg",
      "content_hash": "89f5237283bd154f3bfa0ccc4f0a9c15efe17a3e",
      "alt": "Cap M48865 14x21x8cm gf"
    }
  ],
  "pdfs": [],
  "synced_at": "2026-07-24T06:21:34.958Z"
}